sqlalchemy_fsm/__init__.py
sqlalchemy_fsm/bound.py
sqlalchemy_fsm/cache.py
sqlalchemy_fsm/events.py
sqlalchemy_fsm/exc.py
sqlalchemy_fsm/meta.py
sqlalchemy_fsm/sqltypes.py
sqlalchemy_fsm/transition.py
sqlalchemy_fsm/util.py
sqlalchemy_fsm-2.0.12.dist-info/LICENSE
sqlalchemy_fsm-2.0.12.dist-info/METADATA
sqlalchemy_fsm-2.0.12.dist-info/WHEEL
sqlalchemy_fsm-2.0.12.dist-info/top_level.txt
sqlalchemy_fsm-2.0.12.dist-info/RECORD
