Metadata-Version: 2.1
Name: sqlalchemy-fsm
Version: 2.0.12
Summary: Finite state machine field for sqlalchemy
Home-page: https://github.com/VRGhost/sqlalchemy-fsm
Author: Ilja & Peter
Author-email: ilja@wise.fish
License: MIT
Keywords: sqlalchemy finite state machine fsm
Classifier: Development Status :: 5 - Production/Stable
Classifier: Intended Audience :: Developers
Classifier: License :: OSI Approved :: MIT License
Classifier: Operating System :: OS Independent
Classifier: Programming Language :: Python :: 3
Classifier: Topic :: Database
Requires-Python: >=3.6
License-File: LICENSE
Requires-Dist: SQLAlchemy (>=1.0.0)
Requires-Dist: six (>=1.10.0)
